pyyamb/__init__.py
pyyamb/cut_contigs.py
pyyamb/map.py
pyyamb/pyyamb.py
pyyamb/tetra.py
pyyamb/utils.py
pyYAMB-0.1.4.dist-info/LICENSE
pyYAMB-0.1.4.dist-info/METADATA
pyYAMB-0.1.4.dist-info/WHEEL
pyYAMB-0.1.4.dist-info/entry_points.txt
pyYAMB-0.1.4.dist-info/top_level.txt
pyYAMB-0.1.4.dist-info/RECORD
