Metadata-Version: 2.1
Name: pyYAMB
Version: 0.1.4
Summary: Yet Another Metagenome Binner
Home-page: https://github.com/laxeye/pyyamb
Author: Aleksei Korzhenkov
Author-email: oscypek@ya.ru
Classifier: Development Status :: 4 - Beta
Classifier: Environment :: Console
Classifier: Intended Audience :: Science/Research
Classifier: Programming Language :: Python :: 3
Classifier: License :: OSI Approved :: BSD License
Classifier: Operating System :: POSIX :: Linux
Classifier: Topic :: Scientific/Engineering :: Bio-Informatics
Requires-Python: >=3.8
License-File: LICENSE
Requires-Dist: biopython
Requires-Dist: pandas
Requires-Dist: seaborn
Requires-Dist: pysam
Requires-Dist: matplotlib
Requires-Dist: numpy
Requires-Dist: scikit-learn (<=1.2.2)
Requires-Dist: hdbscan (>=0.8.31)
Requires-Dist: pycoverm
Requires-Dist: regex
